{
	"selectedPlant": "P42 - Ennis",
	"header": "area.createBlend.title",
	"breadcrumbs": [
		{
			"status": "disabled",
			"title": "feature.selectBlend.title"
		},
		{
			"status": "disabled",
			"title": "feature.lotPreferences.title"
		},
		{
			"status": "disabled",
			"title": "feature.draftBlend.title"
		},
		{
			"status": "disabled",
			"title": "feature.finalizeBlend.title"
		},
		{
			"status": "active",
			"title": "feature.saveBlend.title"
		}
	],
	"datacrumbs": [
		{
			"datacrumb": "P42"
		},
		{
			"datacrumb": "3030"
		},
		{
			"datacrumb": "04AG"
		},
		{
			"datacrumb": "MIX 100"
		},
		{
			"datacrumb": "10,000 lbs"
		},
		{
			"datacrumb": "5 components"
		},
		{
			"datacrumb": "Excluded Lots +"
		}
	],
	"draftBlend": {
		"status": "label.optimal",
		"label": "success",
		"bottomLineSpecs": [
			{
				"spec": "label.density",
				"low": "0.1",
				"actual": "0.5",
				"high": "0.9"
			},
			{
				"spec": "label.meltIndex",
				"low": "0.1",
				"actual": "0.5",
				"high": "0.9"
			},
			{
				"spec": "label.izod",
				"low": "0.1",
				"actual": "0.5",
				"high": "0.9"
			},
			{
				"spec": "label.ncls",
				"low": "0.1",
				"actual": "0.5",
				"high": "0.9"
			},
			{
				"spec": "label.sinkFloat",
				"low": "0.1",
				"actual": "0.5",
				"high": "0.9"
			},
			{
				"spec": "label.infrared",
				"low": "0.1",
				"actual": "0.5",
				"high": "0.9"
			}
		],
		"size": "44000",
		"includedLots": [
			{
				"id": "ABCD-1244",
				"type": "flake",
				"badge": "F",
				"sku": "9999ZP",
				"lotNumber": "ZPC021516-1",
				"percentUsed": "24",
				"pounds": "10000",
				"low": "20",
				"high": "80"
			},
			{
				"id": "ABCD-1205",
				"type": "repro",
				"badge": "P",
				"sku": "9999NE",
				"lotNumber": "NEC030816-2",
				"percentUsed": "24",
				"pounds": "10000",
				"low": "20",
				"high": "80"
			},
			{
				"id": "ABCD-1207",
				"type": "regrind",
				"badge": "R",
				"sku": "9999RA",
				"lotNumber": 0,
				"percentUsed": "24",
				"pounds": "10000",
				"low": "20",
				"high": "80"
			},
			{
				"id": "ABCD-1209",
				"type": "virgin",
				"badge": "V",
				"sku": "9999A",
				"lotNumber": "A312016",
				"percentUsed": "24",
				"pounds": "10000",
				"low": "20",
				"high": "80"
			},
			{
				"id": "ABCD-1239",
				"type": "color",
				"badge": "C",
				"sku": "9999B",
				"lotNumber": "B309036",
				"percentUsed": "4",
				"pounds": "4000",
				"low": "20",
				"high": "80"
			}
		],
		"comments": "this is a really good blend"
	}


}
